quebra_frases/__init__.py
quebra_frases/chunks.py
quebra_frases/list_utils.py
quebra_frases/tokenization.py
quebra_frases/tokens.py
quebra_frases/version.py
quebra_frases-0.3.7.dist-info/LICENSE
quebra_frases-0.3.7.dist-info/METADATA
quebra_frases-0.3.7.dist-info/WHEEL
quebra_frases-0.3.7.dist-info/top_level.txt
quebra_frases-0.3.7.dist-info/RECORD
