Metadata-Version: 1.0
Name: quebra-frases
Version: 0.3.7
Summary: quebra_frases chunks strings into byte sized pieces
Home-page: https://github.com/OpenJarbas/quebra_frases
Author: jarbasAi
Author-email: jarbasai@mailfence.com
License: apache-2.0
Platform: UNKNOWN
